lantern_cli/__init__.py
lantern_cli/cli.py
lantern_cli/dynamodb.py
lantern_cli/settings.py
lantern_cli/templates.py
lantern_cli/utils/__init__.py
lantern_cli/utils/json.py
lantern_cli-0.1.11.dist-info/METADATA
lantern_cli-0.1.11.dist-info/WHEEL
lantern_cli-0.1.11.dist-info/entry_points.txt
lantern_cli-0.1.11.dist-info/top_level.txt
lantern_cli-0.1.11.dist-info/RECORD
