Metadata-Version: 2.1
Name: lantern-cli
Version: 0.1.11
Summary: Lantern CLI tool
Home-page: https://github.com/jecel0911/lantern-cli
Author: Jeremias Ceciliano E
Author-email: jeremias.ceciliano@lantern.tech
License: BSD
Platform: any
Classifier: Development Status :: 5 - Production/Stable
Classifier: Environment :: Console
Classifier: Intended Audience :: Developers
Classifier: License :: OSI Approved :: BSD License
Classifier: Operating System :: POSIX
Classifier: Operating System :: MacOS
Classifier: Operating System :: Unix
Classifier: Operating System :: Microsoft :: Windows
Classifier: Programming Language :: Python
Classifier: Programming Language :: Python :: 2
Classifier: Programming Language :: Python :: 3
Classifier: Topic :: Software Development :: Libraries :: Python Modules
Requires-Dist: click
Requires-Dist: cookiecutter
Requires-Dist: boto3
